LICENSE
README.md
setup.py
pyinf/__init__.py
pyinf/_compat.py
pyinf/config.py
pyinf/import_string.py
pyinf/logger.py
pyinf/singleton.py
pyinf.egg-info/PKG-INFO
pyinf.egg-info/SOURCES.txt
pyinf.egg-info/dependency_links.txt
pyinf.egg-info/not-zip-safe
pyinf.egg-info/top_level.txt